unimi_dl/__init__.py
unimi_dl/__main__.py
unimi_dl/cmd.py
unimi_dl/multi_select.py
unimi_dl/platform/__init__.py
unimi_dl/platform/ariel.py
unimi_dl/platform/getPlatform.py
unimi_dl/platform/panopto.py
unimi_dl/platform/platform.py
unimi_dl-0.3.1.dist-info/LICENSE
unimi_dl-0.3.1.dist-info/METADATA
unimi_dl-0.3.1.dist-info/WHEEL
unimi_dl-0.3.1.dist-info/entry_points.txt
unimi_dl-0.3.1.dist-info/top_level.txt
unimi_dl-0.3.1.dist-info/RECORD
