Metadata-Version: 2.1
Name: unimi-dl
Version: 0.3.1
Summary: Script used for downloading videos from Unimi portals
Home-page: https://github.com/SimpoLab/unimi-dl
Author: Alessandro Clerici Lorenzini and Zhifan Chen.
License: attr: unimi_dl.__license__
Project-URL: Bug Tracker, https://github.com/SimpoLab/unimi-dl/issues
Keywords: unimi,download,ariel,panopto,labonline
Platform: UNKNOWN
Classifier: Development Status :: 4 - Beta
Classifier: Environment :: Console
Classifier: License :: OSI Approved :: GNU General Public License v3 (GPLv3)
Classifier: Operating System :: MacOS
Classifier: Operating System :: Microsoft :: Windows
Classifier: Operating System :: POSIX :: Linux
Classifier: Programming Language :: Python
Classifier: Programming Language :: Python :: 3
Classifier: Topic :: Education
Classifier: Topic :: Multimedia
Requires-Python: >=3.8
License-File: LICENSE
Requires-Dist: requests
Requires-Dist: youtube-dl
